CHANGES.rst
CONTRIBUTORS.rst
DEVELOP.rst
LICENSE.GPL
LICENSE.rst
MANIFEST.in
README.rst
constraints.txt
constraints_plone52.txt
constraints_plone60.txt
requirements.txt
requirements_plone52.txt
requirements_plone60.txt
setup.cfg
setup.py
docs/conf.py
docs/index.rst
src/redturtle/__init__.py
src/redturtle.rssservice.egg-info/PKG-INFO
src/redturtle.rssservice.egg-info/SOURCES.txt
src/redturtle.rssservice.egg-info/dependency_links.txt
src/redturtle.rssservice.egg-info/entry_points.txt
src/redturtle.rssservice.egg-info/namespace_packages.txt
src/redturtle.rssservice.egg-info/not-zip-safe
src/redturtle.rssservice.egg-info/requires.txt
src/redturtle.rssservice.egg-info/top_level.txt
src/redturtle/rssservice/__init__.py
src/redturtle/rssservice/configure.zcml
src/redturtle/rssservice/interfaces.py
src/redturtle/rssservice/rss_mixer.py
src/redturtle/rssservice/testing.py
src/redturtle/rssservice/tests/__init__.py
src/redturtle/rssservice/tests/test_rss_mixer.py