Metadata-Version: 2.1
Name: redturtle.rssservice
Version: 2.1.0
Summary: An add-on for Plone
Home-page: https://github.com/collective/redturtle.rssservice
Author: RedTurtle
Author-email: sviluppo@redturtle.it
License: GPL version 2
Project-URL: PyPI, https://pypi.python.org/pypi/redturtle.rssservice
Project-URL: Source, https://github.com/collective/redturtle.rssservice
Project-URL: Tracker, https://github.com/collective/redturtle.rssservice/issues
Keywords: Python Plone
Platform: UNKNOWN
Classifier: Development Status :: 5 - Production/Stable
Classifier: Environment :: Web Environment
Classifier: Framework :: Plone
Classifier: Framework :: Plone :: Addon
Classifier: Framework :: Plone :: 5.2
Classifier: Programming Language :: Python
Classifier: Programming Language :: Python :: 2.7
Classifier: Programming Language :: Python :: 3.6
Classifier: Programming Language :: Python :: 3.7
Classifier: Operating System :: OS Independent
Classifier: License :: OSI Approved :: GNU General Public License v2 (GPLv2)
Requires-Python: >3.6
Provides-Extra: test
